svwebscraper/__init__.py
svwebscraper/cli.py
svwebscraper/exceptions.py
svwebscraper/exporter.py
svwebscraper/webscraper.py
tests/__init__.py
tests/test_exporter.py
tests/test_web_scraper.py
tests/util/__init__.py
tests/util/testdata_loader.py
svscrape-2022.4.dist-info/LICENSE
svscrape-2022.4.dist-info/METADATA
svscrape-2022.4.dist-info/WHEEL
svscrape-2022.4.dist-info/entry_points.txt
svscrape-2022.4.dist-info/top_level.txt
svscrape-2022.4.dist-info/RECORD
