Metadata-Version: 2.1
Name: svscrape
Version: 2022.4
Summary: A webscraper for extracting information of schools from http://schulverzeichnis.eu
Author-email: Florian Wörister <florian.woerister@univie.ac.at>
License: Apache License 2.0
Project-URL: Homepage, https://github.com/fwoerister/SVWebScraper
Keywords: webscraper,schools,austria
Classifier: Programming Language :: Python :: 3
Requires-Python: >=3.8
License-File: LICENSE
Requires-Dist: requests
Requires-Dist: beautifulsoup4
Requires-Dist: click
Provides-Extra: dev
Requires-Dist: pytest ; extra == 'dev'
Requires-Dist: coverage ; extra == 'dev'
